{
  "entries": [
    {
      "key": "PA_ALCHEMICAL_GLASS_CUTTER",
      "name": "planarartifice.research.alchemical_glass_cutter.title",
      "icons": ["planarartifice:glass_cutter_vis"],
      "category": "PLANAR_ARTIFICE",
      "parents": ["PA_GLASSWORKING", "~PA_ALKIMIUM", "~RECHARGEPEDESTAL", "~INFUSION"],
      "meta": ["HIDDEN"],
      "location": [-4, 0],
      "stages": [
        {
          "text": "planarartifice.research.alchemical_glass_cutter.stage.1",
          "required_item": [
            "thaumcraft:phial;1;1;{Aspects:[{amount:10,key:\"auram\"}]}",
            "planarartifice:glass_cutter"
          ]
        },
        {
          "text": "planarartifice.research.alchemical_glass_cutter.stage.2",
          "recipes": ["planarartifice:alchemical_glass_cutter"]
        }
      ]
    },
    {
      "key": "PA_EMISSIVE_GLASS",
      "name": "planarartifice.research.emissive_glass.title",
      "icons": [
        "planarartifice:glass_dark",
        "planarartifice:glass_light",
        "planarartifice:glass_redstone"
      ],
      "category": "PLANAR_ARTIFICE",
      "parents": ["PA_GLASSWORKING", "~BASEALCHEMY"],
      "meta": ["REVERSE"],
      "location": [-3, -1],
      "stages": [
        {
          "text": "planarartifice.research.emissive_glass.stage.1",
          "required_knowledge": [
            "THEORY;ALCHEMY;1"
          ],
          "required_item": [
            "minecraft:glowstone",
            "minecraft:redstone_block"
          ]
        },
        {
          "text": "planarartifice.research.emissive_glass.stage.2",
          "recipes": [
            "planarartifice:glass_dark",
            "planarartifice:glass_light",
            "planarartifice:glass_redstone"
          ]
        }
      ]
    },
    {
      "key": "PA_GLASSWORKING",
      "name": "planarartifice.research.glassworking.title",
      "icons": ["planarartifice:glass_cutter"],
      "category": "PLANAR_ARTIFICE",
      "parents": ["PLANAR_ARTIFICE_BASE"],
      "location": [-2, 0],
      "stages": [
        {
          "text": "planarartifice.research.glassworking.stage.1",
          "required_item": ["minecraft:glass", "minecraft:quartz"],
          "required_research": ["!vitreus"]
        },
        {
          "text": "planarartifice.research.glassworking.stage.2",
          "recipes": [
            "planarartifice:glass_cutter",
            "planarartifice:glass_clear",
            "planarartifice:glass_crystal",
            "planarartifice:glass_hardened"
          ]
        }
      ]
    },
    {
      "key": "PA_PERMEABLE_GLASS",
      "name": "planarartifice.research.permeable_glass.title",
      "icons": [
        "planarartifice:glass_non_living",
        "planarartifice:glass_entity",
        "planarartifice:glass_ethereal"
      ],
      "category": "PLANAR_ARTIFICE",
      "parents": ["PA_GLASSWORKING","~BASEALCHEMY"],
      "meta": ["REVERSE"],
      "location": [-3, 1],
      "stages": [
        {
          "text": "planarartifice.research.permeable_glass.stage.1",
          "required_knowledge": [
            "THEORY;ALCHEMY;1"
          ],
          "required_item": [
            "minecraft:ender_pearl",
            "minecraft:ghast_tear"
          ]
        },
        {
          "text": "planarartifice.research.permeable_glass.stage.2",
          "recipes": [
            "planarartifice:glass_non_living",
            "planarartifice:glass_entity",
            "planarartifice:glass_ethereal"
          ]
        }
      ]
    }
  ]
}
